setup.py
lateral/__init__.py
lateral/api.py
lateral/doc.py
lateral.egg-info/PKG-INFO
lateral.egg-info/SOURCES.txt
lateral.egg-info/dependency_links.txt
lateral.egg-info/requires.txt
lateral.egg-info/top_level.txt