Metadata-Version: 1.0
Name: lateral
Version: 0.0.2
Summary: python interface to Lateral's APIs
Home-page: https://github.com/ftzeng/lateral
Author: Francis Tseng
Author-email: f@frnsys.com
License: MIT
Platform: UNKNOWN
